{"data":{"standardizedTitle":"urn:li:fs_title:1011","companyDetails":{"company":"urn:li:fs_normalized_company:1060","*companyResolutionResult":"urn:li:fs_normalized_company:1060","$recipeTypes":["com.linkedin.voyager.deco.jobs.web.shared.WebJobPostingCompany"],"$type":"com.linkedin.voyager.jobs.JobPostingCompany"},"matchType":null,"employmentStatus":"urn:li:fs_employmentStatus:FULL_TIME","ownerViewEnabled":false,"skillMatches":null,"hiringDashboardViewEnabled":false,"trackingPixelUrl":null,"talentHubJob":false,"formattedLocation":"Rosenheim, Bavaria, Germany","companyDescription":{"attributes":[{"start":12,"length":1,"type":{"$type":"com.linkedin.pemberly.text.LineBreak"},"attributeKindUnion":{"lineBreak":{"$type":"com.linkedin.pemberly.text.LineBreak"}},"$type":"com.linkedin.pemberly.text.Attribute"},{"start":71,"length":1,"type":{"$type":"com.linkedin.pemberly.text.LineBreak"},"attributeKindUnion":{"lineBreak":{"$type":"com.linkedin.pemberly.text.LineBreak"}},"$type":"com.linkedin.pemberly.text.Attribute"},{"start":72,"length":1,"type":{"$type":"com.linkedin.pemberly.text.LineBreak"},"attributeKindUnion":{"lineBreak":{"$type":"com.linkedin.pemberly.text.LineBreak"}},"$type":"com.linkedin.pemberly.text.Attribute"},{"start":83,"length":1,"type":{"$type":"com.linkedin.pemberly.text.LineBreak"},"attributeKindUnion":{"lineBreak":{"$type":"com.linkedin.pemberly.text.LineBreak"}},"$type":"com.linkedin.pemberly.text.Attribute"},{"start":190,"length":1,"type":{"$type":"com.linkedin.pemberly.text.LineBreak"},"attributeKindUnion":{"lineBreak":{"$type":"com.linkedin.pemberly.text.LineBreak"}},"$type":"com.linkedin.pemberly.text.Attribute"},{"start":191,"length":1,"type":{"$type":"com.linkedin.pemberly.text.LineBreak"},"attributeKindUnion":{"lineBreak":{"$type":"com.linkedin.pemberly.text.LineBreak"}},"$type":"com.linkedin.pemberly.text.Attribute"},{"start":202,"length":1,"type":{"$type":"com.linkedin.pemberly.text.LineBreak"},"attributeKindUnion":{"lineBreak":{"$type":"com.linkedin.pemberly.text.LineBreak"}},"$type":"com.linkedin.pemberly.text.Attribute"},{"start":256,"length":1,"type":{"$type":"com.linkedin.pemberly.text.LineBreak"},"attributeKindUnion":{"lineBreak":{"$type":"com.linkedin.pemberly.text.LineBreak"}},"$type":"com.linkedin.pemberly.text.Attribute"},{"start":257,"length":1,"type":{"$type":"com.linkedin.pemberly.text.LineBreak"},"attributeKindUnion":{"lineBreak":{"$type":"com.linkedin.pemberly.text.LineBreak"}},"$type":"com.linkedin.pemberly.text.Attribute"},{"start":394,"length":1,"type":{"$type":"com.linkedin.pemberly.text.LineBreak"},"attributeKindUnion":{"lineBreak":{"$type":"com.linkedin.pemberly.text.LineBreak"}},"$type":"com.linkedin.pemberly.text.Attribute"},{"start":395,"length":1,"type":{"$type":"com.linkedin.pemberly.text.LineBreak"},"attributeKindUnion":{"lineBreak":{"$type":"com.linkedin.pemberly.text.LineBreak"}},"$type":"com.linkedin.pemberly.text.Attribute"}],"text":"Our purpose \nTo create connections that make the unimaginable possible.\n\nOur vision\nA world where limitless connectivity improves lives, redefines business and pioneers a sustainable future.\n\nOur values\nPerseverance, professionalism, respect and integrity.\n\nThe future is a place for purpose & vision – ours are clear, and we invite partners, customers and consumers to join us in our journey. \n\nFor a brighter future. For all. Let's #ImaginePossible","$type":"com.linkedin.pemberly.text.AttributedText"},"jobPostingUrl":"https://www.linkedin.com/jobs/view/4119348735/?trk=jobs_biz_prem_srch","applies":25,"*allJobHiringTeamMembersInjectionResult":"urn:li:fs_jobHiringTeam:4119348735","poster":null,"dashEntityUrn":"urn:li:fsd_jobPosting:4119348735","*employmentStatusResolutionResult":"urn:li:fs_employmentStatus:FULL_TIME","eligibleForLearningCourseRecsUpsell":false,"eligibleForSharingProfileWithPoster":true,"trustReviewDecision":null,"originalListedAt":1736427102000,"entityUrn":"urn:li:fs_normalized_jobPosting:4119348735","workRemoteAllowed":false,"applyMethod":{"companyApplyUrl":"https://jobs.ericsson.com/careers/job/563121760518092?jobPipeline=LinkedIn&domain=ericsson.com","applyStartersPreferenceVoid":true,"inPageOffsiteApply":false,"$type":"com.linkedin.voyager.jobs.OffsiteApply"},"benefitsDataSource":"JOB_POSTER","*savingInfo":"urn:li:fs_jobSavingInfo:4119348735","draftApplicationInfo":null,"formattedJobFunctions":["Other"],"messagingStatus":null,"dashJobPostingCardUrn":"urn:li:fsd_jobPostingCard:(4119348735,JOB_DETAILS)","locationVisibility":"ADDRESS","appeal":null,"expireAt":1739019654000,"$recipeTypes":["com.linkedin.voyager.deco.jobs.web.shared.WebFullJobPosting"],"$type":"com.linkedin.voyager.jobs.JobPosting","standardizedAddresses":null,"claimableByViewer":false,"inferredBenefits":null,"formattedIndustries":["Telecommunications"],"industries":[8],"salaryInsights":{"lockModuleShown":false,"salaryExplorerUrl":"https://www.linkedin.com/salary/","insightExists":false,"jobCompensationAvailable":true,"$type":"com.linkedin.voyager.premium.SalaryInsights"},"country":"urn:li:fs_country:de","jobPosterEntitlements":{"entitledToCopyJob":false,"entitledToAccessJobDashboard":false,"$type":"com.linkedin.voyager.jobs.JobPosterEntitlements","entitledToViewFreeJobInfo":false,"entitledToPromoteJob":false,"entitledToEditJob":false,"entitledToViewBillingInfo":false},"*applyingInfo":"urn:li:fs_jobApplyingInfo:4119348735","locationUrn":"urn:li:fs_geo:103047473","jobApplicationLimitReached":false,"closedAt":null,"new":false,"applicantTrackingSystem":null,"topNRelevanceReasonsInjectionResult":{"*reasons":["urn:li:fs_jobPostingRelevanceReason:(urn:li:fs_normalized_jobPosting:4119348735,ACTIVELY_HIRING_COMPANY)"],"$recipeTypes":["com.linkedin.voyager.deco.jobs.web.shared.WebAllJobPostingRelevanceReasons"],"$type":"com.linkedin.voyager.jobs.relevancereasons.JobPostingRelevanceReasons"},"workplaceTypes":[],"contentSource":"JOBS_PREMIUM_OFFLINE","postalAddress":null,"messagingToken":null,"formattedExperienceLevel":"","yearsOfExperienceMatch":null,"jobFunctions":["OTHR"],"benefits":[],"encryptedPricingParams":"CwIAAAGUYuekHBL1bJ4PdWcjxW1Dz3ikvb3UFW-ZM9wvUwKSV5r7uza_7M0xNn0ODmbpxM-RMn2X12il5XHwvbqQh0sKlMaDHO3eKOPFgTjkVPgxD0sE3DLn5CpTyPGrSjcjpksH-vnXXhGjS0FsOvBuBGaplo6YJJqKiJNSzx-HPEXQOwpcT71pWokDBn48Lv_qS5Y_dtnCvE9pHdk3jw","jobState":"LISTED","trackingUrn":"urn:li:jobPosting:4119348735","description":{"attributes":[{"start":8,"length":1,"type":{"$type":"com.linkedin.pemberly.text.LineBreak"},"attributeKindUnion":{"lineBreak":{"$type":"com.linkedin.pemberly.text.LineBreak"}},"$type":"com.linkedin.pemberly.text.Attribute"},{"start":9,"length":1,"type":{"$type":"com.linkedin.pemberly.text.LineBreak"},"attributeKindUnion":{"lineBreak":{"$type":"com.linkedin.pemberly.text.LineBreak"}},"$type":"com.linkedin.pemberly.text.Attribute"},{"start":0,"length":10,"type":{"$type":"com.linkedin.pemberly.text.Bold"},"attributeKindUnion":{"bold":{"$type":"com.linkedin.pemberly.text.Bold"}},"$type":"com.linkedin.pemberly.text.Attribute"},{"start":328,"length":1,"type":{"$type":"com.linkedin.pemberly.text.LineBreak"},"attributeKindUnion":{"lineBreak":{"$type":"com.linkedin.pemberly.text.LineBreak"}},"$type":"com.linkedin.pemberly.text.Attribute"},{"start":329,"length":1,"type":{"$type":"com.linkedin.pemberly.text.LineBreak"},"attributeKindUnion":{"lineBreak":{"$type":"com.linkedin.pemberly.text.LineBreak"}},"$type":"com.linkedin.pemberly.text.Attribute"},{"start":344,"length":1,"type":{"$type":"com.linkedin.pemberly.text.LineBreak"},"attributeKindUnion":{"lineBreak":{"$type":"com.linkedin.pemberly.text.LineBreak"}},"$type":"com.linkedin.pemberly.text.Attribute"},{"start":345,"length":1,"type":{"$type":"com.linkedin.pemberly.text.LineBreak"},"attributeKindUnion":{"lineBreak":{"$type":"com.linkedin.pemberly.text.LineBreak"}},"$type":"com.linkedin.pemberly.text.Attribute"},{"start":330,"length":16,"type":{"$type":"com.linkedin.pemberly.text.Bold"},"attributeKindUnion":{"bold":{"$type":"com.linkedin.pemberly.text.Bold"}},"$type":"com.linkedin.pemberly.text.Attribute"},{"start":587,"length":1,"type":{"$type":"com.linkedin.pemberly.text.LineBreak"},"attributeKindUnion":{"lineBreak":{"$type":"com.linkedin.pemberly.text.LineBreak"}},"$type":"com.linkedin.pemberly.text.Attribute"},{"start":588,"length":1,"type":{"$type":"com.linkedin.pemberly.text.LineBreak"},"attributeKindUnion":{"lineBreak":{"$type":"com.linkedin.pemberly.text.LineBreak"}},"$type":"com.linkedin.pemberly.text.Attribute"},{"start":605,"length":1,"type":{"$type":"com.linkedin.pemberly.text.LineBreak"},"attributeKindUnion":{"lineBreak":{"$type":"com.linkedin.pemberly.text.LineBreak"}},"$type":"com.linkedin.pemberly.text.Attribute"},{"start":606,"length":1,"type":{"$type":"com.linkedin.pemberly.text.LineBreak"},"attributeKindUnion":{"lineBreak":{"$type":"com.linkedin.pemberly.text.LineBreak"}},"$type":"com.linkedin.pemberly.text.Attribute"},{"start":589,"length":18,"type":{"$type":"com.linkedin.pemberly.text.Bold"},"attributeKindUnion":{"bold":{"$type":"com.linkedin.pemberly.text.Bold"}},"$type":"com.linkedin.pemberly.text.Attribute"},{"start":607,"length":70,"type":{"$type":"com.linkedin.pemberly.text.ListItem"},"attributeKindUnion":{"listItem":{"$type":"com.linkedin.pemberly.text.ListItem"}},"$type":"com.linkedin.pemberly.text.Attribute"},{"start":677,"length":61,"type":{"$type":"com.linkedin.pemberly.text.ListItem"},"attributeKindUnion":{"listItem":{"$type":"com.linkedin.pemberly.text.ListItem"}},"$type":"com.linkedin.pemberly.text.Attribute"},{"start":738,"length":30,"type":{"$type":"com.linkedin.pemberly.text.ListItem"},"attributeKindUnion":{"listItem":{"$type":"com.linkedin.pemberly.text.ListItem"}},"$type":"com.linkedin.pemberly.text.Attribute"},{"start":768,"length":59,"type":{"$type":"com.linkedin.pemberly.text.ListItem"},"attributeKindUnion":{"listItem":{"$type":"com.linkedin.pemberly.text.ListItem"}},"$type":"com.linkedin.pemberly.text.Attribute"},{"start":827,"length":124,"type":{"$type":"com.linkedin.pemberly.text.ListItem"},"attributeKindUnion":{"listItem":{"$type":"com.linkedin.pemberly.text.ListItem"}},"$type":"com.linkedin.pemberly.text.Attribute"},{"start":951,"length":73,"type":{"$type":"com.linkedin.pemberly.text.ListItem"},"attributeKindUnion":{"listItem":{"$type":"com.linkedin.pemberly.text.ListItem"}},"$type":"com.linkedin.pemberly.text.Attribute"},{"start":1024,"length":58,"type":{"$type":"com.linkedin.pemberly.text.ListItem"},"attributeKindUnion":{"listItem":{"$type":"com.linkedin.pemberly.text.ListItem"}},"$type":"com.linkedin.pemberly.text.Attribute"},{"start":1082,"length":70,"type":{"$type":"com.linkedin.pemberly.text.ListItem"},"attributeKindUnion":{"listItem":{"$type":"com.linkedin.pemberly.text.ListItem"}},"$type":"com.linkedin.pemberly.text.Attribute"},{"start":1216,"length":1,"type":{"$type":"com.linkedin.pemberly.text.LineBreak"},"attributeKindUnion":{"lineBreak":{"$type":"com.linkedin.pemberly.text.LineBreak"}},"$type":"com.linkedin.pemberly.text.Attribute"},{"start":1217,"length":1,"type":{"$type":"com.linkedin.pemberly.text.LineBreak"},"attributeKindUnion":{"lineBreak":{"$type":"com.linkedin.pemberly.text.LineBreak"}},"$type":"com.linkedin.pemberly.text.Attribute"},{"start":1152,"length":66,"type":{"$type":"com.linkedin.pemberly.text.ListItem"},"attributeKindUnion":{"listItem":{"$type":"com.linkedin.pemberly.text.ListItem"}},"$type":"com.linkedin.pemberly.text.Attribute"},{"start":607,"length":611,"type":{"ordered":false,"$type":"com.linkedin.pemberly.text.List"},"attributeKindUnion":{"list":{"ordered":false,"$type":"com.linkedin.pemberly.text.List"}},"$type":"com.linkedin.pemberly.text.Attribute"},{"start":1238,"length":1,"type":{"$type":"com.linkedin.pemberly.text.LineBreak"},"attributeKindUnion":{"lineBreak":{"$type":"com.linkedin.pemberly.text.LineBreak"}},"$type":"com.linkedin.pemberly.text.Attribute"},{"start":1239,"length":1,"type":{"$type":"com.linkedin.pemberly.text.LineBreak"},"attributeKindUnion":{"lineBreak":{"$type":"com.linkedin.pemberly.text.LineBreak"}},"$type":"com.linkedin.pemberly.text.Attribute"},{"start":1218,"length":22,"type":{"$type":"com.linkedin.pemberly.text.Bold"},"attributeKindUnion":{"bold":{"$type":"com.linkedin.pemberly.text.Bold"}},"$type":"com.linkedin.pemberly.text.Attribute"},{"start":1240,"length":126,"type":{"$type":"com.linkedin.pemberly.text.ListItem"},"attributeKindUnion":{"listItem":{"$type":"com.linkedin.pemberly.text.ListItem"}},"$type":"com.linkedin.pemberly.text.Attribute"},{"start":1366,"length":80,"type":{"$type":"com.linkedin.pemberly.text.ListItem"},"attributeKindUnion":{"listItem":{"$type":"com.linkedin.pemberly.text.ListItem"}},"$type":"com.linkedin.pemberly.text.Attribute"},{"start":1446,"length":41,"type":{"$type":"com.linkedin.pemberly.text.ListItem"},"attributeKindUnion":{"listItem":{"$type":"com.linkedin.pemberly.text.ListItem"}},"$type":"com.linkedin.pemberly.text.Attribute"},{"start":1487,"length":44,"type":{"$type":"com.linkedin.pemberly.text.ListItem"},"attributeKindUnion":{"listItem":{"$type":"com.linkedin.pemberly.text.ListItem"}},"$type":"com.linkedin.pemberly.text.Attribute"},{"start":1531,"length":49,"type":{"$type":"com.linkedin.pemberly.text.ListItem"},"attributeKindUnion":{"listItem":{"$type":"com.linkedin.pemberly.text.ListItem"}},"$type":"com.linkedin.pemberly.text.Attribute"},{"start":1580,"length":44,"type":{"$type":"com.linkedin.pemberly.text.ListItem"},"attributeKindUnion":{"listItem":{"$type":"com.linkedin.pemberly.text.ListItem"}},"$type":"com.linkedin.pemberly.text.Attribute"},{"start":1674,"length":1,"type":{"$type":"com.linkedin.pemberly.text.LineBreak"},"attributeKindUnion":{"lineBreak":{"$type":"com.linkedin.pemberly.text.LineBreak"}},"$type":"com.linkedin.pemberly.text.Attribute"},{"start":1675,"length":1,"type":{"$type":"com.linkedin.pemberly.text.LineBreak"},"attributeKindUnion":{"lineBreak":{"$type":"com.linkedin.pemberly.text.LineBreak"}},"$type":"com.linkedin.pemberly.text.Attribute"},{"start":1624,"length":52,"type":{"$type":"com.linkedin.pemberly.text.ListItem"},"attributeKindUnion":{"listItem":{"$type":"com.linkedin.pemberly.text.ListItem"}},"$type":"com.linkedin.pemberly.text.Attribute"},{"start":1240,"length":436,"type":{"ordered":false,"$type":"com.linkedin.pemberly.text.List"},"attributeKindUnion":{"list":{"ordered":false,"$type":"com.linkedin.pemberly.text.List"}},"$type":"com.linkedin.pemberly.text.Attribute"}],"text":"About Us\n\nOur Industrialization & Verification team plays a crucial role in our Research & Development (R&D) group, focusing on creating efficient and reliable manufacturing processes for cutting-edge antenna products. We work in a fast-paced, innovative environment and are dedicated to advancing antenna production technology.\n\nAbout The Role\n\nWe’re seeking a skilled Production Line Planner to elevate our antenna manufacturing process. In this role, you’ll design and optimize production lines, using the latest manufacturing technology to improve efficiency, speed, and reliability.\n\nWhat You Will Do\n\nDevelop new production concepts and design efficient production lines.Optimize production times and costs through strategic setups.Design ergonomic workstations.Balance production lines and calculate manufacturing times.Implement LEAN principles, including Total Productive Maintenance (TPM) and One Piece Flow, as well as conduct time studies.Track and improve process KPIs (such as Overall Equipment Effectiveness).Specify equipment needs and identify critical spare parts.Integrate insights from past projects into new manufacturing concepts.Support problem-solving efforts and conduct root cause analyses.\n\nThe Skills You Bring\n\nA university degree in a technical field, such as mechanical engineering or production technology, or a similar qualification.Strong experience in production line planning, manufacturing technology, or R&D.Solid knowledge of manufacturing methods.Strong analytical and organizational skills.A structured, solutions-focused approach to work.Excellent teamwork and communication skills.Proficiency in English (German skills are a plus).\n\n]]>","$type":"com.linkedin.pemberly.text.AttributedText"},"hiringTeamEntitlements":null,"formattedEmploymentStatus":"Full-time","repostedJobPosting":null,"title":"Production Line Planner (m/f/d)","skillsDescription":null,"trustReviewSla":null,"jobRegion":null,"thirdPartySourced":false,"views":123,"*standardizedTitleResolutionResult":"urn:li:fs_title:1011","eligibleForReferrals":false,"listedAt":1736427654000,"degreeMatches":null,"jobPostingId":4119348735,"allowedToEdit":false,"sourceDomain":"jobs.ericsson.com"},"included":[{"trackingUrn":null,"followingType":"DEFAULT","followingCount":null,"$type":"com.linkedin.voyager.common.FollowingInfo","entityUrn":"urn:li:fs_followingInfo:urn:li:company:1060","following":false,"dashFollowingStateUrn":"urn:li:fsd_followingState:urn:li:fsd_company:1060","followerCount":2078770},{"resumeDownloadUrl":null,"appliedTime":null,"resumeFileType":null,"entityUrn":"urn:li:fs_jobApplyingInfo:4119348735","applied":false,"activities":null,"closed":false,"viewedByJobPosterAt":null,"resumeFileName":null,"appliedAt":null,"$type":"com.linkedin.voyager.entities.shared.JobApplyingInfo"},{"saved":false,"entityUrn":"urn:li:fs_jobSavingInfo:4119348735","savedAt":null,"dashSaveStateUrn":"urn:li:fsd_saveState:(SAVE,urn:li:fsd_jobPosting:4119348735)","$type":"com.linkedin.voyager.entities.shared.JobSavingInfo"},{"entityUrn":"urn:li:fs_jobHiringTeam:4119348735","hiringTeamMembers":[],"$recipeTypes":["com.linkedin.voyager.deco.jobs.web.shared.WebAllJobHiringTeamMembers"],"$type":"com.linkedin.voyager.jobs.JobHiringTeam"},{"jobPostingRelevanceReasonDetail":{"activelyHiringCompany":true,"$recipeTypes":["com.linkedin.voyager.deco.jobs.web.shared.WebJobPostingRelevanceReasonDetail"],"relevanceReasonFlavor":"ACTIVELY_HIRING_COMPANY","$type":"com.linkedin.voyager.jobs.relevancereasons.JobPostingRelevanceReasonDetail"},"entityUrn":"urn:li:fs_jobPostingRelevanceReason:(urn:li:fs_normalized_jobPosting:4119348735,ACTIVELY_HIRING_COMPANY)","jobPosting":"urn:li:fs_normalized_jobPosting:4119348735","details":null,"$recipeTypes":["com.linkedin.voyager.deco.jobs.web.shared.relevancereasons.WebListedJobPostingRelevanceReason"],"$type":"com.linkedin.voyager.jobs.relevancereasons.JobPostingRelevanceReason"},{"localizedName":"Full-time","entityUrn":"urn:li:fs_employmentStatus:FULL_TIME","$recipeTypes":["com.linkedin.voyager.deco.jobs.shared.WebFullEmploymentStatus"],"$type":"com.linkedin.voyager.jobs.shared.EmploymentStatus"},{"localizedName":"Production Planner","entityUrn":"urn:li:fs_title:1011","$recipeTypes":["com.linkedin.voyager.deco.jobs.web.shared.WebFullTitle"],"$type":"com.linkedin.voyager.jobs.shared.Title"},{"description":"Our purpose \nTo create connections that make the unimaginable possible.\n\nOur vision\nA world where limitless connectivity improves lives, redefines business and pioneers a sustainable future.\n\nOur values\nPerseverance, professionalism, respect and integrity.\n\nThe future is a place for purpose & vision – ours are clear, and we invite partners, customers and consumers to join us in our journey. \n\nFor a brighter future. For all. Let's #ImaginePossible","staffCount":109262,"viewerFollowingJobsUpdates":false,"entityUrn":"urn:li:fs_normalized_company:1060","staffCountRange":{"start":10001,"$type":"com.linkedin.voyager.organization.shared.StaffCountRange"},"headquarter":{"geographicArea":"Stockholm","country":"SE","city":"Kista","line1":"Torshamnsgatan 21","$type":"com.linkedin.common.Address"},"logo":{"image":{"$type":"com.linkedin.common.VectorImage","rootUrl":"https://media.licdn.com/dms/image/v2/C4E0BAQGm9tH6lKJ-Gg/company-logo_","artifacts":[{"width":200,"expiresAt":1744848000000,"fileIdentifyingUrlPathSegment":"200_200/company-logo_200_200/0/1632729373904/ericsson_logo?e=1744848000&v=beta&t=BYbPqJdU9ktGTXns9RXuocfJXoZkdwSsehTz4NhbLUw","$type":"com.linkedin.common.VectorArtifact","height":200},{"width":100,"expiresAt":1744848000000,"fileIdentifyingUrlPathSegment":"100_100/company-logo_100_100/0/1632729373904/ericsson_logo?e=1744848000&v=beta&t=d38Aq61o14RbGqE3emgZjfLTxqXXrW43xe_qusCp-do","$type":"com.linkedin.common.VectorArtifact","height":100},{"width":400,"expiresAt":1744848000000,"fileIdentifyingUrlPathSegment":"400_400/company-logo_400_400/0/1632729373904/ericsson_logo?e=1744848000&v=beta&t=ApInMyCsEyjZAae5eLitAWdT3WPGvLHogtskSJnODkA","$type":"com.linkedin.common.VectorArtifact","height":400}]},"type":"SQUARE_LOGO","$type":"com.linkedin.voyager.organization.CompanyLogoImage"},"universalName":"ericsson","specialities":["5G","Internet of Things","Mobile broadband","Communication services","Managed services","Fixed broadband","LTE","3G","4G","OSS","BSS","Cloud","Network","Telecom","ICT","IT","IP","Technology For Good","Sustainability","IoT","Intelligent Transport Systems","AI","R&D"],"coverPhoto":{"$type":"com.linkedin.voyager.common.MediaProcessorImage","id":"/AAEAAQAAAAAAAAw0AAAAJDYxZTNjOWQ5LWQ0MzAtNGY4Yy1iNjUzLTE4MDhmNWFhMDQxYw.png"},"*followingInfo":"urn:li:fs_followingInfo:urn:li:company:1060","$recipeTypes":["com.linkedin.voyager.deco.organization.shared.WebJobCompany"],"url":"https://www.linkedin.com/company/ericsson","$type":"com.linkedin.voyager.organization.Company","lcpTreatment":true,"industries":["Telecommunications"],"name":"Ericsson","backgroundCoverImage":{"image":{"$type":"com.linkedin.common.VectorImage","rootUrl":"https://media.licdn.com/dms/image/v2/C4E1BAQFAuKU3UVzpuQ/company-background_","artifacts":[{"width":1537,"expiresAt":1737432000000,"fileIdentifyingUrlPathSegment":"10000/company-background_10000/0/1632729477969/ericsson_cover?e=1737432000&v=beta&t=qpiMRu25LBfcun2to6hYdi8VfMnF_afMKnD2vueSeno","$type":"com.linkedin.common.VectorArtifact","height":768},{"width":400,"expiresAt":1737432000000,"fileIdentifyingUrlPathSegment":"400/company-background_400/0/1632729477969/ericsson_cover?e=1737432000&v=beta&t=ZX4R2miyCUJLMl4OYcUvnXEcNptagtbSRCpRZ1Lsulw","$type":"com.linkedin.common.VectorArtifact","height":199},{"width":200,"expiresAt":1737432000000,"fileIdentifyingUrlPathSegment":"200/company-background_200/0/1632729477969/ericsson_cover?e=1737432000&v=beta&t=QUbAbPVfrf7z9THlRt1uOvGNFLePiwpyy-07Qx-fx2A","$type":"com.linkedin.common.VectorArtifact","height":99}]},"$type":"com.linkedin.voyager.identity.profile.BackgroundImage","cropInfo":{"width":1537,"x":0,"y":272,"$type":"com.linkedin.voyager.identity.profile.ImageCropInfo","height":260}}}]}